<?xml version="1.0" encoding="utf-8"?>
<case>
  <ID>EL1e447f58ac585509ce32bb90f90cd052</ID>
  <patient>
    <case_date></case_date>
    <gender>male</gender>
    <patient_initials>ασδαδαδασδδ</patient_initials>
    <age>18</age>
    <circumstances>λξασνδπιασηδσπιδηδπιασδηνασπιδθηασπ</circumstances>
  </patient>
  <new_patient>
    <description>
      <main_complaint>
        <origin>asdas</origin>
        <causative_factors>asda</causative_factors>
        <modalities>asd</modalities>
        <occurrence_time>asdas</occurrence_time>
        <body_side>ασδασδασδασδασδασδδαδασδασδασδασδασ</body_side>
        <appearence_frequency>ada</appearence_frequency>
        <pain_desc>asd</pain_desc>
        <complaint_ext>asdas</complaint_ext>
        <other_complaints></other_complaints>
      </main_complaint>
      <diagnosis>
        <conv_med_presc>asdas</conv_med_presc>
        <lab_tests>
          <desc></desc>
          <file></file>
        </lab_tests>
        <pre_homeo_presc></pre_homeo_presc>
      </diagnosis>
      <medical_history>
        <personal>
          <therapies_vaccination>asd</therapies_vaccination>
          <traumas>asd</traumas>
          <infections>asd</infections>
          <other></other>
        </personal>
        <family>
          <diseases>asdas</diseases>
        </family>
      </medical_history>
      <physical>
        <reactions></reactions>
        <sleeping_habits></sleeping_habits>
        <food_modalities></food_modalities>
        <menstruation></menstruation>
      </physical>
      <mental_emotional>asdas</mental_emotional>
    </description>
    <analysis>
      <prognosis>
        <anatomopathological></anatomopathological>
        <personal_medical_history>asdas</personal_medical_history>
        <family_medical_history>asdas</family_medical_history>
        <level_of_health>3</level_of_health>
        <conclusion>asdas</conclusion>
      </prognosis>
      <symptoms_selection>
        <peculiar>asdas</peculiar>
        <intense>asd</intense>
      </symptoms_selection>
      <repertorization>
        <desc></desc>
        <file_url></file_url>
      </repertorization>
      <remedies_differentiation>asd</remedies_differentiation>
      <prescription>
        <remedy>asd</remedy>
        <potency>asd</potency>
        <regimen>asd</regimen>
        <other_notes>asd</other_notes>
      </prescription>
    </analysis>
  </new_patient>
  <followups>
    <followup>
      <number>1</number>
      <followup_date></followup_date>
      <conv_med_presc>asdsadas</conv_med_presc>
      <lab_tests>
        <desc></desc>
        <file></file>
      </lab_tests>
      <reaction>asdas</reaction>
      <analysis>asdas</analysis>
      <conclusion>asdas</conclusion>
      <repertorization>
        <desc>asdasd</desc>
        <file_url></file_url>
      </repertorization>
      <prescription>
        <remedy>asdasd</remedy>
        <potency>asdasd</potency>
        <regimen>asdasda</regimen>
        <other_notes>asdasdas</other_notes>
      </prescription>
    </followup>
    <followup>
      <number>2</number>
      <followup_date></followup_date>
      <conv_med_presc>dfasfa</conv_med_presc>
      <lab_tests>
        <desc></desc>
        <file></file>
      </lab_tests>
      <reaction>dsasd</reaction>
      <analysis>asfas</analysis>
      <conclusion>asfasf</conclusion>
      <repertorization>
        <desc>asfa</desc>
        <file_url></file_url>
      </repertorization>
      <prescription>
        <remedy>sdgsdgsd</remedy>
        <potency>asdgsdg</potency>
        <regimen>adsgag</regimen>
        <other_notes>asdgas</other_notes>
      </prescription>
    </followup>
  </followups>
</case>
